concentrator_calculator/__init__.py
concentrator_calculator/__main__.py
concentrator_calculator/time_calculator.py
concentrator_calculator/data/centrifuge_data.xlsx
concentrator_calculator-1.0.4.dist-info/LICENSE
concentrator_calculator-1.0.4.dist-info/METADATA
concentrator_calculator-1.0.4.dist-info/WHEEL
concentrator_calculator-1.0.4.dist-info/entry_points.txt
concentrator_calculator-1.0.4.dist-info/top_level.txt
concentrator_calculator-1.0.4.dist-info/RECORD
