Metadata-Version: 2.1
Name: concentrator-calculator
Version: 1.0.4
Summary: Tool to calculate vacuum centrifuge times
Home-page: https://github.com/DominikBuchner/concentrator_calculator
Author: Dominik Buchner
Author-email: dominik.buchner524@googlemail.com
License: MIT
Platform: UNKNOWN
Classifier: Programming Language :: Python :: 3
Classifier: License :: OSI Approved :: MIT License
Classifier: Operating System :: OS Independent
Requires-Python: >=3.6
Requires-Dist: PySimpleGUI (>=4.19.0)
Requires-Dist: numpy (>=1.18.4)
Requires-Dist: pandas (>=1.0.4)
Requires-Dist: scipy (>=1.4.1)
